blue_st_sdk/__init__.py
blue_st_sdk/debug_console.py
blue_st_sdk/feature.py
blue_st_sdk/manager.py
blue_st_sdk/node.py
blue_st_sdk/python_utils.py
blue_st_sdk/advertising_data/__init__.py
blue_st_sdk/advertising_data/ble_advertising_data.py
blue_st_sdk/advertising_data/ble_advertising_data_parser.py
blue_st_sdk/advertising_data/blue_st_advertising_data.py
blue_st_sdk/advertising_data/blue_st_advertising_data_parser.py
blue_st_sdk/features/__init__.py
blue_st_sdk/features/device_timestamp_feature.py
blue_st_sdk/features/feature_accelerometer.py
blue_st_sdk/features/feature_activity_recognition.py
blue_st_sdk/features/feature_audio_adpcm.py
blue_st_sdk/features/feature_audio_adpcm_sync.py
blue_st_sdk/features/feature_audio_scene_classification.py
blue_st_sdk/features/feature_gyroscope.py
blue_st_sdk/features/feature_humidity.py
blue_st_sdk/features/feature_magnetometer.py
blue_st_sdk/features/feature_pressure.py
blue_st_sdk/features/feature_proximity.py
blue_st_sdk/features/feature_proximity_gesture.py
blue_st_sdk/features/feature_stepper_motor.py
blue_st_sdk/features/feature_switch.py
blue_st_sdk/features/feature_temperature.py
blue_st_sdk/features/field.py
blue_st_sdk/features/audio/__init__.py
blue_st_sdk/features/audio/adpcm/__init__.py
blue_st_sdk/features/audio/adpcm/bv_audio_sync_manager.py
blue_st_sdk/features/audio/adpcm/feature_audio_adpcm.py
blue_st_sdk/features/audio/adpcm/feature_audio_adpcm_sync.py
blue_st_sdk/features/standard_characteristics/__init__.py
blue_st_sdk/features/standard_characteristics/feature_heart_rate.py
blue_st_sdk/features/standard_characteristics/standard_characteristic_to_feature_map.py
blue_st_sdk/firmware_upgrade/__init__.py
blue_st_sdk/firmware_upgrade/firmware_upgrade.py
blue_st_sdk/firmware_upgrade/firmware_upgrade_nucleo.py
blue_st_sdk/firmware_upgrade/utils/__init__.py
blue_st_sdk/firmware_upgrade/utils/firmware_file.py
blue_st_sdk/firmware_upgrade/utils/stm32crc32.py
blue_st_sdk/utils/__init__.py
blue_st_sdk-1.4.0.dist-info/LICENSE
blue_st_sdk-1.4.0.dist-info/METADATA
blue_st_sdk-1.4.0.dist-info/WHEEL
blue_st_sdk-1.4.0.dist-info/top_level.txt
blue_st_sdk-1.4.0.dist-info/RECORD
